st_button/__init__.py
st_button/example.py
st_button-0.0.2.dist-info/licenses/LICENSE
st_button-0.0.2.dist-info/METADATA
st_button-0.0.2.dist-info/WHEEL
st_button-0.0.2.dist-info/top_level.txt
st_button-0.0.2.dist-info/RECORD
